treevis/__init__.py
treevis/bt.py
treevis/colors.py
treevis/node.py
treevis-0.1.0.dist-info/LICENSE
treevis-0.1.0.dist-info/WHEEL
treevis-0.1.0.dist-info/METADATA
treevis-0.1.0.dist-info/RECORD
