Metadata-Version: 2.1
Name: treevis
Version: 0.1.0
Summary: A library for displaying a binary tree in plain text.
Author-email: "Konstantin Y. Rybakov" <viocost@gmail.com>
Classifier: License :: OSI Approved :: MIT License
Project-URL: Home, https://github.com/viocost/treevis
